fflive_cli.py
fflive/__init__.py
fflive/audio.py
fflive/image.py
fflive/stream.py
fflive/video.py
fflive-1.4.1.dist-info/METADATA
fflive-1.4.1.dist-info/WHEEL
fflive-1.4.1.dist-info/entry_points.txt
fflive-1.4.1.dist-info/top_level.txt
fflive-1.4.1.dist-info/RECORD
