Metadata-Version: 2.4
Name: fflive
Version: 1.4.1
Summary: fflive python package url [https://github.com/jiashaokun/fflive]
Home-page: https://github.com/jiashaokun/fflive
Author: SkeyJIA
Author-email: 363604236@qq.com
License: MIT Licence
Keywords: python fflive
Platform: any
Dynamic: author
Dynamic: author-email
Dynamic: description
Dynamic: home-page
Dynamic: keywords
Dynamic: license
Dynamic: platform
Dynamic: summary
